setup.py
cmp_is_back/__init__.py
cmp_is_back.egg-info/PKG-INFO
cmp_is_back.egg-info/SOURCES.txt
cmp_is_back.egg-info/dependency_links.txt
cmp_is_back.egg-info/top_level.txt