Metadata-Version: 1.1
Name: cmp-is-back
Version: 0.1
Summary: (Just for fun) Bring cmp() and __cmp__ back.
Home-page: UNKNOWN
Author: cheny0y0 <anony> + REGE
Author-email: UNKNOWN
License: UNKNOWN
Platform: UNKNOWN
Classifier: Programming Language :: Python :: 1
Classifier: Programming Language :: Python :: 1.3
Classifier: Programming Language :: Python :: 1.4
Classifier: Programming Language :: Python :: 1.5
Classifier: Programming Language :: Python :: 1.6
Classifier: Programming Language :: Python :: 2
Classifier: Programming Language :: Python :: 2.0
Classifier: Programming Language :: Python :: 2.1
Classifier: Programming Language :: Python :: 2.2
Classifier: Programming Language :: Python :: 2.3
Classifier: Programming Language :: Python :: 2.4
Classifier: Programming Language :: Python :: 2.5
Classifier: Programming Language :: Python :: 2.6
Classifier: Programming Language :: Python :: 2.7
Classifier: Programming Language :: Python :: 3
Classifier: Programming Language :: Python :: 3.0
Classifier: Programming Language :: Python :: 3.1
Classifier: Programming Language :: Python :: 3.2
Classifier: Programming Language :: Python :: 3.3
Classifier: Programming Language :: Python :: 3.4
Classifier: Programming Language :: Python :: 3.5
Classifier: Programming Language :: Python :: 3.6
Classifier: Programming Language :: Python :: 3.7
Classifier: Programming Language :: Python :: 3.8
Classifier: Programming Language :: Python :: 3.9
Classifier: Programming Language :: Python :: 3.10
Classifier: Programming Language :: Python :: 3.11
Classifier: Programming Language :: Python :: 3.12
Classifier: Operating System :: OS Independent
